kiwi_pdf_chunker/__init__.py
kiwi_pdf_chunker/box_processing.py
kiwi_pdf_chunker/config.py
kiwi_pdf_chunker/env_config.py
kiwi_pdf_chunker/image_processing.py
kiwi_pdf_chunker/main.py
kiwi_pdf_chunker/models.py
kiwi_pdf_chunker/pdf.py
kiwi_pdf_chunker-0.3.3.dist-info/licenses/LICENSE
kiwi_pdf_chunker-0.3.3.dist-info/METADATA
kiwi_pdf_chunker-0.3.3.dist-info/WHEEL
kiwi_pdf_chunker-0.3.3.dist-info/top_level.txt
kiwi_pdf_chunker-0.3.3.dist-info/RECORD
