Metadata-Version: 2.4
Name: kiwi-pdf-chunker
Version: 0.3.3
Summary: A tool for parsing PDF document layouts and chunking content
Author-email: Vahan Martirosyan / Kiwi Data <vahan@kiwidata.com>
Maintainer-email: Vahan Martirosyan <vahan@kiwidata.com>
License: MIT
Project-URL: Homepage, https://github.com/Neo-License/cv_doc_chunker
Project-URL: Repository, https://github.com/Neo-License/cv_doc_chunker
Project-URL: Issues, https://github.com/Neo-License/cv_doc_chunker/issues
Keywords: pdf,ocr,parsing,document,layout,detection,chunking,cv
Classifier: Development Status :: 3 - Alpha
Classifier: Intended Audience :: Developers
Classifier: Intended Audience :: Science/Research
Classifier: License :: OSI Approved :: MIT License
Classifier: Operating System :: OS Independent
Classifier: Programming Language :: Python :: 3
Classifier: Programming Language :: Python :: 3.10
Classifier: Programming Language :: Python :: 3.11
Classifier: Topic :: Scientific/Engineering :: Image Recognition
Classifier: Topic :: Text Processing :: Indexing
Requires-Python: >=3.10
License-File: LICENSE
Requires-Dist: pymupdf==1.25.3
Requires-Dist: PyPDF2==3.0.1
Requires-Dist: doclayout-yolo==0.0.3
Requires-Dist: pdf2image==1.17.0
Requires-Dist: opencv-python==4.10.0.84
Requires-Dist: huggingface_hub==0.30.0
Requires-Dist: tqdm==4.67.1
Requires-Dist: pillow==11.1.0
Requires-Dist: numpy==1.26.4
Requires-Dist: click==8.1.8
Requires-Dist: python-dotenv==1.0.1
Requires-Dist: azure-ai-documentintelligence==1.0.2
Requires-Dist: azure-core==1.33.0
Requires-Dist: pytesseract==0.3.13
Requires-Dist: openai==1.77.0
Requires-Dist: docling==2.55.0
Requires-Dist: pdfplumber==0.11.7
Requires-Dist: pandas==2.3.2
Requires-Dist: requests==2.32.5
Requires-Dist: transformers==4.53.0
Dynamic: license-file
